{
  "name": "Henri Tremblay",
  "bio": "Henri est Java Champion, JavaOne Rock Star et Montréal JUG leader. Il a développé les concepts des mocks de classes au sein des projets EasyMock et Objenesis dont il est le project leader. Il est actuellement directeur de TS Imagine Canada.\n\nSes centres d’intérêt sont l’optimisation et la productivité. Ceux-ci étant parfois plus liés qu’on ne pourrait le penser. Il est un conférencier récurrent sur ces sujets.\n\nIl essaie d’être utile.",
  "position": "Managing director @ TS Imagine",
  "image": "speakers-2025/henri-tremblay.png",
  "time": "2025-11-28T14:00:00",
  "track": 1,
  "title": "Social Network Kata: Le bon rythme",
  "description": "Comprendre la mécanique d'un kata, du TDD et du développement.",
  "github": null,
  "linkedin": null,
  "website": "http://blog.tremblay.pro/"
}
